{
 "JEM": [
  [
   "HRT FINANCIAL LP",
   "2026-07-09T22:25:47.001008+00:00",
   186684
  ]
 ],
 "WRAP": [
  [
   "SHULMAN JOHN D",
   "2026-07-09T23:46:22.218484+00:00",
   110000
  ]
 ],
 "UUUU": [
  [
   "Bhappu Ross R.",
   "2026-07-09T23:46:22.218484+00:00",
   967920
  ]
 ],
 "GLOO": [
  [
   "Beck Scott Arthur",
   "2026-07-10T21:03:24.921142+00:00",
   3499999
  ]
 ],
 "BGDE": [
  [
   "Endeavor Blockchain, LLC",
   "2026-07-10T22:13:30.037179+00:00",
   16700000
  ]
 ],
 "CV": [
  [
   "HARARI ELIYAHOU ET AL",
   "2026-07-11T03:13:53.063117+00:00",
   495117
  ]
 ],
 "NTSK": [
  [
   "ICONIQ Strategic Partners VIII Holdings, L.P.",
   "2026-07-11T03:13:53.063117+00:00",
   7216048
  ],
  [
   "Griffith William J.G.",
   "2026-07-11T03:13:53.063117+00:00",
   7216080
  ]
 ],
 "IPX": [
  [
   "Arima Anastasios",
   "2026-07-13T14:36:35.782922+00:00",
   497227
  ],
  [
   "Hannigan Todd",
   "2026-07-13T14:36:35.782922+00:00",
   1881165
  ]
 ],
 "EOI": [
  [
   "Gaffney Charles",
   "2026-07-13T18:47:06.263829+00:00",
   502705
  ]
 ]
}
